autosnip.py
venv/lib/python3.12/site-packages/autosnip.py
venv/lib/python3.12/site-packages/venv/lib/python3.12/site-packages/autosnip.py
autosnip-0.1.4.dist-info/METADATA
autosnip-0.1.4.dist-info/WHEEL
autosnip-0.1.4.dist-info/entry_points.txt
autosnip-0.1.4.dist-info/licenses/LICENSE
autosnip-0.1.4.dist-info/RECORD
