Metadata-Version: 2.4
Name: autosnip
Version: 0.1.4
Summary: automatically clean up voice recordings
Project-URL: Homepage, https://github.com/mqnc/autosnip
Project-URL: Issues, https://github.com/mqnc/autosnip/issues
Author: Mirko Kunze
License-File: LICENSE
Classifier: License :: OSI Approved :: MIT License
Classifier: Operating System :: OS Independent
Classifier: Programming Language :: Python :: 3
Requires-Python: >=3.0
Requires-Dist: audioop-lts>=0.2.2; python_version >= '3.13'
Requires-Dist: numpy>=2.3.3
Requires-Dist: soundfile>=0.13.1
Requires-Dist: vosk>=0.3.45
